{
 "packages":
 [
  {
   "name": "custom_boards",
   "maintainer": "DarkCaster",
   "websiteURL": "https://github.com/DarkCaster/Arduino-Custom-Boards",
   "email": "",
   "help":
   {
    "online": "https://github.com/DarkCaster/Arduino-Custom-Boards"
   },
   "platforms":
   [
{
 "name": "Custom AVR board-definitions",
 "architecture": "avr",
 "version": "2018.5.23",
 "category": "Contributed",
 "help":
 {
  "online": "https://github.com/DarkCaster/Arduino-Custom-Boards"
 },
 "url": "https://raw.githubusercontent.com/DarkCaster/Arduino-Custom-Boards/master/packages/custom_boards_2018.5.23.zip",
 "archiveFileName": "custom_boards_2018.5.23.zip",
 "checksum": "SHA-256:d3f7cfebcc071e6e88df51ef7ccbd485e70f80266463c290bdd2b0bcb872cba3",
 "size": "7062",
 "boards":
 [
  {"name": "ATmega328"},
  {"name": "ATmega1284"}
 ],
 "toolsDependencies":
 [
  {
   "packager": "arduino",
   "name": "avrdude",
   "version": "6.3.0-arduino9"
  },
  {
   "packager": "arduino",
   "name": "avr-gcc",
   "version": "4.9.2-atmel3.5.4-arduino2"
  }
 ]
}   ],
   "tools": [ ]
  }
 ]
}
